{
  "id": "pr-37926",
  "source_pr": {
    "number": 37926,
    "url": "https://github.com/pingcap/tidb/pull/37926",
    "title": "test,ddl: fix data race in `TestCancel`",
    "body": "Signed-off-by: YangKeao <yangkeao@chunibyo.icu>\r\n\r\n### What problem does this PR solve?\r\n\r\n1. Some variables in the test is used concurrently. I used an atomic variable to read/write them to fix the data race\r\n2. The callback struct is also concurrently modified. I add a clone method to copy it explicitly. \r\n    I have also considered other solutions, for example using non-pointer receiver to implement the callback, so it can be copied automatically when passing into the functions. However, as this struct contains a `*BaseCallback`, it could cause more problem when misused.\r\n\r\nIssue Number: close #37757 \r\n\r\n"
  },
  "pr_merged_at": "2022-09-19T16:45:01+08:00",
  "test": {
    "type": "unit",
    "path": "ddl/callback_test.go",
    "name": "TestCancel"
  },
  "symptoms": [
    "test,ddl: fix data race in `TestCancel`"
  ],
  "failure_signature": "test,ddl: fix data race in `TestCancel`",
  "root_cause_categories": [
    "schema_change_race",
    "concurrency_data_race"
  ],
  "review_smells": [
    "ddl_without_wait",
    "async_schema_propagation"
  ],
  "fix_pattern": "test,ddl: fix data race in `TestCancel`",
  "evidence_links": [
    "https://github.com/pingcap/tidb/pull/37926",
    "https://github.com/pingcap/tidb/pull/37926.patch"
  ],
  "patch_url": "https://github.com/pingcap/tidb/pull/37926.patch",
  "changed_files": [
    "ddl/callback_test.go",
    "ddl/cancel_test.go",
    "ddl/column_change_test.go"
  ],
  "triage": {
    "sources": [
      "manual_triage",
      "explicit_flaky_signal"
    ],
    "evidence": [
      "evidence: test,ddl: fix data race in `TestCancel`",
      "files: ddl/callback_test.go, ddl/cancel_test.go, ddl/column_change_test.go"
    ]
  },
  "analysis": "PR title: test,ddl: fix data race in `TestCancel`\nPR url: https://github.com/pingcap/tidb/pull/37926\nTriage sources: manual_triage, explicit_flaky_signal\nTriage summary: test,ddl: fix data race in `TestCancel`\nChanged files (3): ddl/callback_test.go, ddl/cancel_test.go, ddl/column_change_test.go\nPatch url: https://github.com/pingcap/tidb/pull/37926.patch\nPicked test: type=unit path=ddl/callback_test.go name=TestCancel"
}